azure/mgmt/dns/__init__.py
azure/mgmt/dns/_configuration.py
azure/mgmt/dns/_dns_management_client.py
azure/mgmt/dns/_serialization.py
azure/mgmt/dns/_version.py
azure/mgmt/dns/models.py
azure/mgmt/dns/py.typed
azure/mgmt/dns/aio/__init__.py
azure/mgmt/dns/aio/_configuration.py
azure/mgmt/dns/aio/_dns_management_client.py
azure/mgmt/dns/v2016_04_01/__init__.py
azure/mgmt/dns/v2016_04_01/_configuration.py
azure/mgmt/dns/v2016_04_01/_dns_management_client.py
azure/mgmt/dns/v2016_04_01/_patch.py
azure/mgmt/dns/v2016_04_01/_vendor.py
azure/mgmt/dns/v2016_04_01/_version.py
azure/mgmt/dns/v2016_04_01/aio/__init__.py
azure/mgmt/dns/v2016_04_01/aio/_configuration.py
azure/mgmt/dns/v2016_04_01/aio/_dns_management_client.py
azure/mgmt/dns/v2016_04_01/aio/_patch.py
azure/mgmt/dns/v2016_04_01/aio/operations/__init__.py
azure/mgmt/dns/v2016_04_01/aio/operations/_patch.py
azure/mgmt/dns/v2016_04_01/aio/operations/_record_sets_operations.py
azure/mgmt/dns/v2016_04_01/aio/operations/_zones_operations.py
azure/mgmt/dns/v2016_04_01/models/__init__.py
azure/mgmt/dns/v2016_04_01/models/_dns_management_client_enums.py
azure/mgmt/dns/v2016_04_01/models/_models_py3.py
azure/mgmt/dns/v2016_04_01/models/_patch.py
azure/mgmt/dns/v2016_04_01/operations/__init__.py
azure/mgmt/dns/v2016_04_01/operations/_patch.py
azure/mgmt/dns/v2016_04_01/operations/_record_sets_operations.py
azure/mgmt/dns/v2016_04_01/operations/_zones_operations.py
azure/mgmt/dns/v2018_03_01_preview/__init__.py
azure/mgmt/dns/v2018_03_01_preview/_configuration.py
azure/mgmt/dns/v2018_03_01_preview/_dns_management_client.py
azure/mgmt/dns/v2018_03_01_preview/_patch.py
azure/mgmt/dns/v2018_03_01_preview/_vendor.py
azure/mgmt/dns/v2018_03_01_preview/_version.py
azure/mgmt/dns/v2018_03_01_preview/aio/__init__.py
azure/mgmt/dns/v2018_03_01_preview/aio/_configuration.py
azure/mgmt/dns/v2018_03_01_preview/aio/_dns_management_client.py
azure/mgmt/dns/v2018_03_01_preview/aio/_patch.py
azure_mgmt_dns-8.1.0.dist-info/LICENSE
azure_mgmt_dns-8.1.0.dist-info/METADATA
azure_mgmt_dns-8.1.0.dist-info/WHEEL
azure_mgmt_dns-8.1.0.dist-info/top_level.txt
azure_mgmt_dns-8.1.0.dist-info/RECORD
